{"api-examples.md":"BuPdUqOD","index.md":"CMSOhm9F","markdown-examples.md":"B_zSDvAl","views_fitness_2025_202507.md":"BzH8oZlL","views_fitness_2025_202508.md":"BIAMpajf","views_fitness_chart_index.md":"DjNcuCbi","views_fitness_index.md":"CtrqUAEp","views_food_2025_202507.md":"CDFKSLXJ","views_food_index.md":"C_Q-qCn2","views_study_guitar_board_index.md":"Be9y8UCz","views_study_guitar_index.md":"CoLypnmf","views_study_guitar_music_index.md":"0pN92LcI","views_study_guitar_music_test.md":"B4IHkGJG","views_study_guitar_practice_index.md":"B1WH-gYN","views_study_index.md":"Dn1Blxkc","views_study_music_index.md":"1ue7AvMd","views_study_ne_annex_compare.md":"DHDxn-Gt","views_study_ne_annex_formula.md":"lcsfjR65","views_study_ne_annex_index.md":"CKdM_VUS","views_study_ne_annex_protocol.md":"HT9-fKQT","views_study_ne_annex_wifi7.md":"CuWIcflH","views_study_ne_annex_wireshart.md":"COgGhkgJ","views_study_ne_exam_2020_bottom.md":"e1LqRPLR","views_study_ne_exam_2020_top.md":"aCrHgZBU","views_study_ne_exam_2021_bottom.md":"CMQblaLY","views_study_ne_exam_2021_top.md":"D-PNy9XU","views_study_ne_exam_2022_bottom.md":"nSVT5AKf","views_study_ne_exam_2022_top.md":"Bv11il3H","views_study_ne_exam_2023_bottom.md":"B6WjIMbI","views_study_ne_exam_2023_top.md":"DkL0oocW","views_study_ne_exam_2024_bottom.md":"CUr8Lhyl","views_study_ne_exam_2024_top.md":"DDkUfFfm","views_study_ne_exam_2025_top.md":"DNTyIPSn","views_study_ne_exam_index.md":"ByCzuRTH","views_study_ne_index.md":"C2zejYs_","views_study_ne_practice_1.实验环境的准备.md":"B0Ai0TH3","views_study_ne_practice_10.wireshark抓包分析dns协议.md":"Dyl0Cybv","views_study_ne_practice_11.wireshark抓包分析ftp协议.md":"O-dt_lXA","views_study_ne_practice_12.vrro_mstp_dhcp综合配置实验.md":"CL4g0GoM","views_study_ne_practice_13.bgp或mpls_vpn实践配置.md":"CqPXabfE","views_study_ne_practice_2.划分vlan.md":"Dj466-Xs","views_study_ne_practice_3.mstp生成树.md":"DMhrZIOj","views_study_ne_practice_4.rstp快速生成树.md":"D1lI6b55","views_study_ne_practice_5.静态路由与bfd联动.md":"7QeZ-c3A","views_study_ne_practice_6.rip路由协议配置.md":"Dz1MdrBO","views_study_ne_practice_7.ospf路由协议配置.md":"BBW-p-HT","views_study_ne_practice_8.配置ipv6和isatap隧道.md":"BhMpsm_7","views_study_ne_practice_9.wireshark抓包分析https协议.md":"CcZOPk8X","views_study_ne_practice_index.md":"sRKUd_uG","views_study_ne_question_choice.md":"DTy_wHLn","views_study_ne_question_error.md":"dUFHqE3H","views_study_ne_question_index.md":"bejkpj8B","views_study_ne_question_shortanswer.md":"WoSC6r1O","views_study_ne_theory_index.md":"X2iZ5YC0","views_study_ne_theory_一_1.网络体系结构.md":"DfpyJhXz","views_study_ne_theory_一_2.数据通信基础.md":"CpP970qv","views_study_ne_theory_一_3.传输媒体.md":"RHXBo7nH","views_study_ne_theory_一_4.信道复用技术.md":"DD3L7KOv","views_study_ne_theory_一_5.数字传输系统.md":"C21nSh81","views_study_ne_theory_一_6.互联网接入技术.md":"lCkd0U0M","views_study_ne_theory_七_1.acl访问控制列表.md":"I7akwkWf","views_study_ne_theory_七_2.nat网络地址转换.md":"B_v_JmKb","views_study_ne_theory_七_3.路由策略.md":"DpBPM3_Z","views_study_ne_theory_七_4.策略路由.md":"BN4zjGto","views_study_ne_theory_七_5.vrrp虚拟路由冗余协议.md":"RdjjfciV","views_study_ne_theory_七_6.bfd与nqa链路检测技术.md":"CDQGUP5C","views_study_ne_theory_七_7.链路聚合与设备堆叠.md":"CYoKgCth","views_study_ne_theory_三_1.网络层基本概念.md":"SvEuRDP7","views_study_ne_theory_三_2.ip地址.md":"NQkG1z2s","views_study_ne_theory_三_3.ip协议.md":"DhWj5o__","views_study_ne_theory_三_4.arp协议.md":"DOt7ePft","views_study_ne_theory_三_5.icmp协议.md":"BJWj1t4C","views_study_ne_theory_九_1.密码技术.md":"B89w-PfU","views_study_ne_theory_九_2.病毒和网络攻击.md":"6yYSAi6E","views_study_ne_theory_二_1.数据链路层.md":"Dv4sKMw6","views_study_ne_theory_二_10.stp生成树协议.md":"DEsc3Gkh","views_study_ne_theory_二_2.ppp协议.md":"DOmU6cmK","views_study_ne_theory_二_3.hdlc协议.md":"2vkSgx6y","views_study_ne_theory_二_4.arq机制.md":"BjeNNYgV","views_study_ne_theory_二_5.csma_cd协议.md":"fHZ79v3p","views_study_ne_theory_二_6.以太网mac层.md":"C5LVpOed","views_study_ne_theory_二_7.以太网类型.md":"DwA4hah3","views_study_ne_theory_二_8.vlan虚拟局域网.md":"Buv6EeN2","views_study_ne_theory_二_9.vlan高级应用.md":"t-4Wa72G","views_study_ne_theory_五_1.dns协议.md":"BhAGyk8T","views_study_ne_theory_五_2.dhcp协议.md":"BNjKwmhF","views_study_ne_theory_五_3.ftp协议.md":"D3xV28Gl","views_study_ne_theory_五_4.http协议.md":"CLUTPNVT","views_study_ne_theory_五_5.邮件协议.md":"BOAWvBW5","views_study_ne_theory_五_6.telnet协议.md":"DBKTO2HO","views_study_ne_theory_五_7.snmp协议.md":"BPz0db2W","views_study_ne_theory_八_1.综合布线系统.md":"Cws7Ly-i","views_study_ne_theory_八_2.存储技术.md":"DB5DIAQY","views_study_ne_theory_六_1.静态路由协议.md":"DulPgH_p","views_study_ne_theory_六_2.rip路由协议.md":"BJb84Mdu","views_study_ne_theory_六_3.ospf路由协议.md":"B80AHC1g","views_study_ne_theory_六_4.is-is路由协议.md":"C8-w0dLL","views_study_ne_theory_六_5.bgp路由协议.md":"DqUmK8XA","views_study_ne_theory_六_6.bgp配置实践.md":"vwiajibL","views_study_ne_theory_四_1.传输层协议概述.md":"DwJYhExU","views_study_ne_theory_四_2.udp协议.md":"C02CZT6Z","views_study_ne_theory_四_3.tcp协议概述.md":"CkNuUx1S","views_study_ne_theory_四_4.tcp首部格式.md":"DefPv842","views_study_ne_theory_四_5.tcp滑动窗口.md":"CjWjBlI8","views_study_ne_theory_四_6.tcp拥塞控制.md":"3GkNBjmw","views_study_ne_theory_四_7.tcp连接管理.md":"C2vxdNbH"}
